{
  "version": 6,
  "settings": {
    "fallDelayMs": 60,
    "rotationDurationMs": 120
  },
  "levels": [
    {
      "name": "02 - Base",
      "maxMoves": 2,
      "locked": true,
      "difficulty": 2,
      "biome": "forest",
      "solution": "RL",
      "map": [
        ".............",
        "...B.........",
        "..#######....",
        "..#.....#....",
        "..#.....#....",
        "..#.#####....",
        ".............",
        ".............",
        "....###.#.##.",
        "....#......#.",
        "....#.....A..",
        "....########.",
        "............."
      ]
    },
    {
      "name": "03 - Base",
      "maxMoves": 5,
      "locked": true,
      "difficulty": 3,
      "biome": "desert",
      "solution": "RLLRL",
      "map": [
        ".............",
        ".............",
        "....A........",
        ".............",
        ".........##B.",
        ".....###.....",
        ".........###.",
        "..........##.",
        "..####.......",
        ".........##..",
        ".............",
        ".............",
        "............."
      ]
    },
    {
      "name": "04 - Base",
      "maxMoves": 4,
      "locked": true,
      "difficulty": 4,
      "biome": "ice",
      "solution": "LLLL",
      "map": [
        ".............",
        ".............",
        "........#..A.",
        "........#....",
        ".............",
        "........#....",
        ".......B#....",
        "......#####..",
        ".....#######.",
        "........#....",
        "........#....",
        ".............",
        "............."
      ]
    },
    {
      "name": "05 - Base",
      "maxMoves": 3,
      "locked": true,
      "difficulty": 5,
      "biome": "rainbow",
      "solution": "LLL",
      "map": [
        ".............",
        ".............",
        "....A........",
        ".............",
        ".......#####.",
        "........B#...",
        ".....#####...",
        ".........#...",
        "...####..#...",
        ".........#...",
        ".#.##....#...",
        ".............",
        "............."
      ]
    },
    {
      "name": "06 - Bouton",
      "maxMoves": 5,
      "locked": true,
      "difficulty": 6,
      "biome": "cosmic",
      "solution": "LLLLL",
      "map": [
        ".............",
        ".............",
        ".............",
        "....#B.......",
        "..###.##D##..",
        "....#........",
        "....#........",
        "..S.#....A...",
        "....#........",
        ".###########.",
        "....#........",
        ".............",
        "............."
      ]
    },
    {
      "name": "07 - Bouton",
      "maxMoves": 3,
      "locked": true,
      "difficulty": 7,
      "biome": "forest",
      "solution": "LRR",
      "map": [
        ".............",
        ".............",
        "..B#.........",
        "...######....",
        "...#.........",
        "..S..........",
        "...#.........",
        "...#.........",
        "...D.........",
        ".###.........",
        ".A.#.........",
        ".............",
        "............."
      ]
    },
    {
      "name": "08 - Bouton",
      "maxMoves": 6,
      "locked": true,
      "difficulty": 8,
      "biome": "desert",
      "solution": "RLRLRL",
      "map": [
        ".............",
        ".............",
        ".............",
        ".............",
        ".....#.......",
        "....B....##..",
        "..####.......",
        ".....####....",
        ".D...........",
        ".............",
        "....S........",
        "...A.........",
        "............."
      ]
    },
    {
      "name": "09 - Bouton",
      "maxMoves": 5,
      "locked": true,
      "difficulty": 9,
      "biome": "ice",
      "solution": "LRRLL",
      "map": [
        ".............",
        ".............",
        ".............",
        ".............",
        ".....#.O###D.",
        ".....#.......",
        ".A...####....",
        ".....#B......",
        "...####......",
        ".....#.......",
        ".#.###.......",
        "...........S.",
        "............."
      ]
    },
    {
      "name": "10 - Jeanne labyrinthe",
      "maxMoves": 999,
      "locked": true,
      "difficulty": 10,
      "biome": "desert",
      "requiredMechanic": "button",
      "solution": "LRRRLLL",
      "solutionUses": [
        "O",
        "S"
      ],
      "designNote": "Niveau de Jeanne injecté dans le chapitre bouton/porte.",
      "validation": {
        "testedSolvable": true,
        "mainBrickRequired": true,
        "forcedPosition": 10,
        "source": "capture / ancien Nouveau niveau 21"
      },
      "map": [
        ".............",
        ".....#.......",
        ".#...#.......",
        "....S#...##..",
        "....##..#.#..",
        "........D.#..",
        "...#....D.#..",
        "...#...##.#..",
        "...#...#B.#..",
        "...#....##...",
        "...#.A#......",
        "...#.##......",
        "............."
      ]
    },
    {
      "name": "11 - Bouton",
      "maxMoves": 5,
      "locked": true,
      "difficulty": 11,
      "biome": "rainbow",
      "solution": "RRRRR",
      "map": [
        ".............",
        ".S...........",
        ".............",
        ".............",
        "....#..####D.",
        "...B#........",
        "....#####....",
        "....#........",
        "...####......",
        "....#........",
        ".##.#........",
        "...A.........",
        "............."
      ]
    },
    {
      "name": "12 - Danger",
      "maxMoves": 5,
      "locked": true,
      "difficulty": 12,
      "biome": "cosmic",
      "solution": "LLLLL",
      "map": [
        ".............",
        "..........S..",
        "......#...X..",
        "......#......",
        "......#......",
        "......#......",
        "..########D..",
        "......#......",
        "......#......",
        "......#B.....",
        "..A####.##...",
        ".............",
        "............."
      ]
    },
    {
      "name": "13 - Danger",
      "maxMoves": 5,
      "locked": true,
      "difficulty": 13,
      "biome": "forest",
      "solution": "LLLLL",
      "map": [
        ".............",
        ".......A.....",
        "....#........",
        "....#........",
        "....#....S...",
        "....#........",
        "....#X.......",
        "....#B.......",
        "..##D##......",
        ".#.#####O....",
        "....#........",
        ".............",
        "............."
      ]
    },
    {
      "name": "14 - Danger",
      "maxMoves": 6,
      "locked": true,
      "difficulty": 14,
      "biome": "desert",
      "solution": "RRLRLR",
      "map": [
        ".............",
        ".............",
        ".............",
        "....###......",
        "...A.........",
        "........###..",
        "..###........",
        "...........X.",
        ".............",
        ".##.......S..",
        ".B..#D##.....",
        "....###...###",
        "............."
      ]
    },
    {
      "name": "15 - Danger",
      "maxMoves": 8,
      "locked": true,
      "difficulty": 15,
      "biome": "ice",
      "solution": "LLLLLLRL",
      "map": [
        ".............",
        ".............",
        ".............",
        "......X......",
        ".##......O.##",
        "..###........",
        "....A###.....",
        ".............",
        ".............",
        ".......#D#...",
        "........B....",
        "...S......###",
        "............."
      ]
    },
    {
      "name": "16 - Danger",
      "maxMoves": 3,
      "locked": true,
      "difficulty": 16,
      "biome": "rainbow",
      "solution": "RRR",
      "map": [
        ".............",
        ".............",
        ".............",
        ".............",
        "....X...#....",
        "..#######.#..",
        "........#B.S.",
        "........#....",
        "........#....",
        ".#######D###.",
        "......A.#....",
        "....X........",
        "............."
      ]
    },
    {
      "name": "16 - Danger",
      "maxMoves": 7,
      "locked": true,
      "difficulty": 16,
      "biome": "rainbow",
      "solution": "RRRRRRR",
      "map": [
        ".............",
        ".............",
        ".............",
        ".............",
        "....X...#....",
        "..#######.#..",
        "........#B.S.",
        "........#....",
        "........#....",
        ".#######D###.",
        "......A.#....",
        "....X........",
        "............."
      ]
    },
    {
      "name": "17 - Rotateur",
      "maxMoves": 8,
      "locked": true,
      "difficulty": 17,
      "biome": "cosmic",
      "solution": "RRRLRRRR",
      "map": [
        ".............",
        ".###.........",
        ".B.....R.....",
        ".....D.##....",
        "...###.......",
        ".............",
        "..####.......",
        "......##.....",
        ".............",
        "....S.....X..",
        "....AX.......",
        ".............",
        "............."
      ]
    },
    {
      "name": "18 - Rotateur",
      "maxMoves": 8,
      "locked": true,
      "difficulty": 18,
      "biome": "forest",
      "solution": "RRRRRRLR",
      "map": [
        ".............",
        ".......L.....",
        "..##.####....",
        "..#.....#....",
        "..#.....#....",
        "..##.####....",
        "...B.........",
        ".........X...",
        ".X..#.######.",
        "....#...S.AD.",
        "....#......#.",
        "....####.###.",
        "............."
      ]
    },
    {
      "name": "19 - Rotateur",
      "maxMoves": 8,
      "locked": true,
      "difficulty": 19,
      "biome": "desert",
      "solution": "RRLLRRLL",
      "map": [
        ".............",
        ".............",
        "..###A##.....",
        "..#.....D....",
        "..#.X..S#....",
        "..#.#####....",
        ".............",
        "....X........",
        ".....###.###.",
        "....#........",
        "....#......#.",
        ".R.B###.O###.",
        "............."
      ]
    },
    {
      "name": "20 - Rotateur",
      "maxMoves": 12,
      "locked": true,
      "difficulty": 20,
      "biome": "ice",
      "solution": "LLLLRRLRLLLL",
      "map": [
        ".............",
        ".............",
        "..####..#..R.",
        "..#.....#....",
        "..#A....O....",
        "..#####.#....",
        "......X......",
        "...S..L...B..",
        "....##.#..##.",
        "...X#......#.",
        "....#........",
        "....##D###.#.",
        "............."
      ]
    },
    {
      "name": "21 - Rotateur",
      "maxMoves": 9,
      "locked": true,
      "difficulty": 21,
      "biome": "rainbow",
      "solution": "RLLLRRRRR",
      "map": [
        ".............",
        "..X..........",
        ".............",
        "..L..........",
        ".....X######.",
        "......#S.A...",
        "..R..##.#....",
        "......#......",
        "...####......",
        "......#B.....",
        ".###D.#......",
        ".............",
        "............."
      ]
    },
    {
      "name": "22 - Premier sourire",
      "maxMoves": 6,
      "locked": true,
      "difficulty": 22,
      "biome": "love",
      "solution": "RRRLLL",
      "map": [
        ".............",
        ".............",
        "...######....",
        "...#.....#...",
        "....#DD#B#...",
        ".......##....",
        "..........##.",
        ".####.....A#.",
        "...S#........",
        "......######.",
        ".............",
        "..#..........",
        "............."
      ]
    },
    {
      "name": "23 - Message maladroit",
      "maxMoves": 7,
      "locked": true,
      "difficulty": 23,
      "biome": "garden",
      "solution": "RLLLRRR",
      "map": [
        ".............",
        ".......#.....",
        ".......#...#.",
        "..##...#S....",
        "..#.#..##....",
        "..#.D........",
        "..#.D....#...",
        "..#.##...#...",
        "..#.B#...#...",
        "...##....#...",
        "......#A.#...",
        "......##.#...",
        "............."
      ]
    },
    {
      "name": "24 - Café annulé",
      "maxMoves": 8,
      "locked": true,
      "difficulty": 24,
      "biome": "kiss",
      "solution": "LLRRRLLL",
      "map": [
        ".............",
        "..........#..",
        ".............",
        ".######......",
        "........#S...",
        ".#A.....####.",
        ".##..........",
        "....##.......",
        "...#B#DD#....",
        "...#.....#...",
        "....######...",
        ".............",
        "............."
      ]
    },
    {
      "name": "25 - Silence radio",
      "maxMoves": 9,
      "locked": true,
      "difficulty": 25,
      "biome": "starry",
      "solution": "LLLRRRLLL",
      "map": [
        ".............",
        "......##.#...",
        "......#A.#...",
        "...##....#...",
        "..#.B#...#...",
        "..#.##...#...",
        "..#.D....#...",
        "..#.D........",
        "..#.#..##....",
        "..##...#S....",
        ".......#...#.",
        ".......#.....",
        "............."
      ]
    },
    {
      "name": "26 - Mauvais timing",
      "maxMoves": 9,
      "locked": true,
      "difficulty": 26,
      "biome": "rainbow",
      "solution": "RLLLLLRRR",
      "map": [
        ".............",
        "...#.##......",
        "...#.A#......",
        "...#....##...",
        "...#...#B.#..",
        "...#...##.#..",
        "...#....D.#..",
        "........D.#..",
        "....##..#.#..",
        "....S#...##..",
        ".#...#.......",
        ".....#.......",
        "............."
      ]
    },
    {
      "name": "27 - Deuxième chance",
      "maxMoves": 3,
      "locked": true,
      "difficulty": 27,
      "biome": "forest",
      "solution": "RRR",
      "map": [
        ".............",
        ".........A...",
        "........#.##.",
        "........#....",
        "......####...",
        "........#....",
        "....#####....",
        "........#B...",
        ".D####..#....",
        ".............",
        ".............",
        "...........S.",
        "............."
      ]
    },
    {
      "name": "28 - Conversation bancale",
      "maxMoves": 3,
      "locked": true,
      "difficulty": 28,
      "biome": "love",
      "solution": "LLL",
      "map": [
        ".............",
        "...A.........",
        ".##.#........",
        "....#........",
        "...####......",
        "....#........",
        "....#####....",
        "...B#........",
        "....#..####D.",
        ".............",
        ".............",
        ".S...........",
        "............."
      ]
    },
    {
      "name": "29 - Presque rendez-vous",
      "maxMoves": 5,
      "locked": true,
      "difficulty": 29,
      "biome": "desert",
      "solution": "LLLLL",
      "map": [
        ".............",
        "...........S.",
        ".............",
        ".............",
        ".D####..#....",
        "........#B...",
        "....#####....",
        "........#....",
        "......####...",
        "........#....",
        "........#.##.",
        ".........A...",
        "............."
      ]
    },
    {
      "name": "30 - Profil mystère",
      "maxMoves": 3,
      "locked": true,
      "difficulty": 30,
      "biome": "garden",
      "solution": "LLL",
      "map": [
        ".............",
        ".............",
        "...##.####A..",
        ".....B#......",
        "......#......",
        "......#......",
        "..D########..",
        "......#......",
        "......#......",
        "......#......",
        "..X...#......",
        "..S..........",
        "............."
      ]
    },
    {
      "name": "31 - Trop loin",
      "maxMoves": 3,
      "locked": true,
      "difficulty": 31,
      "biome": "ice",
      "solution": "RRR",
      "map": [
        ".............",
        ".............",
        "..A####.##...",
        "......#B.....",
        "......#......",
        "......#......",
        "..########D..",
        "......#......",
        "......#......",
        "......#......",
        "......#...X..",
        "..........S..",
        "............."
      ]
    },
    {
      "name": "32 - Trop vite",
      "maxMoves": 4,
      "locked": true,
      "difficulty": 32,
      "biome": "kiss",
      "solution": "RLLL",
      "map": [
        ".............",
        ".............",
        "..A...#......",
        "..#...#......",
        "..#...#......",
        "..#...#......",
        "..#########..",
        "...B..#......",
        "..#...#......",
        "..#...#......",
        "......D...XS.",
        ".............",
        "............."
      ]
    },
    {
      "name": "33 - Trop compliqué",
      "maxMoves": 4,
      "locked": true,
      "difficulty": 33,
      "biome": "cosmic",
      "solution": "LLLL",
      "map": [
        ".............",
        ".............",
        ".SX...D......",
        "......#...#..",
        "......#...#..",
        "......#..B...",
        "..#########..",
        "......#...#..",
        "......#...#..",
        "......#...#..",
        "......#...A..",
        ".............",
        "............."
      ]
    },
    {
      "name": "34 - Le bon détour",
      "maxMoves": 5,
      "locked": true,
      "difficulty": 34,
      "biome": "starry",
      "solution": "RRRRR",
      "map": [
        ".............",
        "..S..........",
        "..X...#......",
        "......#......",
        "......#......",
        "......#......",
        "..D########..",
        "......#......",
        "......#......",
        ".....B#......",
        "...##.####A..",
        ".............",
        "............."
      ]
    },
    {
      "name": "35 - Papillons prudents",
      "maxMoves": 3,
      "locked": true,
      "difficulty": 35,
      "biome": "rainbow",
      "solution": "LLL",
      "map": [
        ".............",
        ".............",
        "........#....",
        "....O#####.#.",
        "......##D##..",
        ".......B#....",
        ".......X#....",
        "........#....",
        "...S....#....",
        "........#....",
        "........#....",
        ".....A.......",
        "............."
      ]
    },
    {
      "name": "36 - Promesse fragile",
      "maxMoves": 3,
      "locked": true,
      "difficulty": 36,
      "biome": "love",
      "solution": "RRR",
      "map": [
        ".............",
        ".............",
        "....#........",
        ".#.#####O....",
        "..##D##......",
        "....#B.......",
        "....#X.......",
        "....#........",
        "....#....S...",
        "....#........",
        "....#........",
        ".......A.....",
        "............."
      ]
    },
    {
      "name": "37 - Le doute",
      "maxMoves": 5,
      "locked": true,
      "difficulty": 37,
      "biome": "garden",
      "solution": "LLRRR",
      "map": [
        ".............",
        ".....A.......",
        "........#....",
        "........#....",
        "...S....#....",
        "........#....",
        ".......X#....",
        ".......B#....",
        "......##D##..",
        "....O#####.#.",
        "........#....",
        ".............",
        "............."
      ]
    },
    {
      "name": "38 - Le retour",
      "maxMoves": 6,
      "locked": true,
      "difficulty": 38,
      "biome": "kiss",
      "solution": "LLRLRL",
      "map": [
        ".............",
        ".............",
        ".............",
        "......###....",
        ".........A...",
        "..###........",
        "........###..",
        ".X...........",
        ".............",
        "..S.......##.",
        ".....##D#..B.",
        "###...###....",
        "............."
      ]
    },
    {
      "name": "39 - Nouvelle rencontre",
      "maxMoves": 1,
      "locked": true,
      "difficulty": 39,
      "biome": "forest",
      "solution": "L",
      "map": [
        "....#......#.",
        "....#......#.",
        "...........#.",
        "....O....#...",
        ".........DB..",
        "......#..#...",
        "...X..#......",
        "......#......",
        ".....#A......",
        ".....#.....S.",
        "....##.......",
        "....#........",
        "............."
      ]
    },
    {
      "name": "40 - Signes contradictoires",
      "maxMoves": 2,
      "locked": true,
      "difficulty": 40,
      "biome": "starry",
      "solution": "RL",
      "map": [
        ".............",
        "###......S...",
        "....B........",
        "...#D#.......",
        ".............",
        ".............",
        ".....###A....",
        "........###..",
        "##.O......##.",
        "......X......",
        ".............",
        ".............",
        "............."
      ]
    },
    {
      "name": "41 - L’étincelle",
      "maxMoves": 2,
      "locked": true,
      "difficulty": 41,
      "biome": "rainbow",
      "solution": "LR",
      "map": [
        ".............",
        "...S......###",
        "........B....",
        ".......#D#...",
        ".............",
        ".............",
        "....A###.....",
        "..###........",
        ".##......O.##",
        "......X......",
        ".............",
        ".............",
        "............."
      ]
    },
    {
      "name": "42 - Rendez-vous réel",
      "maxMoves": 3,
      "locked": true,
      "difficulty": 42,
      "biome": "love",
      "solution": "RRL",
      "map": [
        ".............",
        "........#....",
        ".......##....",
        ".S.....#.....",
        "......A#.....",
        "......#......",
        "......#..X...",
        "...#..#......",
        "..BD.........",
        "...#....O....",
        ".#...........",
        ".#......#....",
        ".#......#...."
      ]
    },
    {
      "name": "43 - Main tendue",
      "maxMoves": 8,
      "locked": true,
      "difficulty": 43,
      "biome": "garden",
      "solution": "RRRRRRLR",
      "map": [
        ".............",
        ".............",
        ".............",
        "......X......",
        "##.O......##.",
        "........###..",
        ".....###A....",
        ".............",
        ".............",
        "...#D#.......",
        "....B........",
        "###......S...",
        "............."
      ]
    },
    {
      "name": "44 - Pas si simple",
      "maxMoves": 4,
      "locked": true,
      "difficulty": 44,
      "biome": "cosmic",
      "solution": "RRRR",
      "map": [
        ".............",
        "......S..#...",
        ".....#...#...",
        "......B..#...",
        "....#####D#..",
        ".....#...#...",
        ".....#...#A..",
        ".....#...#...",
        "....X#...#.X.",
        ".....#...#...",
        ".....#...#...",
        ".........#...",
        "............."
      ]
    },
    {
      "name": "45 - Ça recommence",
      "maxMoves": 5,
      "locked": true,
      "difficulty": 45,
      "biome": "kiss",
      "solution": "RRRRR",
      "map": [
        ".............",
        "........X....",
        "....#.A......",
        ".###D#######.",
        "....#........",
        "....#........",
        ".S.B#........",
        "..#.#######..",
        "....#...X....",
        ".............",
        ".............",
        ".............",
        "............."
      ]
    },
    {
      "name": "46 - Enfin fluide",
      "maxMoves": 5,
      "locked": true,
      "difficulty": 46,
      "biome": "starry",
      "solution": "LLLLL",
      "map": [
        ".............",
        "....X........",
        "......A.#....",
        ".#######D###.",
        "........#....",
        "........#....",
        "........#B.S.",
        "..#######.#..",
        "....X...#....",
        ".............",
        ".............",
        ".............",
        "............."
      ]
    },
    {
      "name": "47 - Le vrai choix",
      "maxMoves": 6,
      "locked": true,
      "difficulty": 47,
      "biome": "rainbow",
      "solution": "RRRRRR",
      "map": [
        ".............",
        "...#.........",
        "...#...#.....",
        "...#...#.....",
        ".X.#...#X....",
        "...#...#.....",
        "..A#...#.....",
        "...#...#.....",
        "..#D#####....",
        "...#..B......",
        "...#...#.....",
        "...#..S......",
        "............."
      ]
    },
    {
      "name": "48 - Dernier virage",
      "maxMoves": 7,
      "locked": true,
      "difficulty": 48,
      "biome": "love",
      "solution": "LLLLLLL",
      "map": [
        ".............",
        ".............",
        ".............",
        ".............",
        "....#...X....",
        "..#.#######..",
        ".S.B#........",
        "....#........",
        "....#........",
        ".###D#######.",
        "....#.A......",
        "........X....",
        "............."
      ]
    },
    {
      "name": "49 - Presque sûr",
      "maxMoves": 6,
      "locked": true,
      "difficulty": 49,
      "biome": "garden",
      "solution": "RLRRRR",
      "map": [
        ".............",
        ".............",
        ".......XA....",
        "..X.....S....",
        ".............",
        ".....##......",
        ".......####..",
        ".............",
        ".......###...",
        "....##.D.....",
        ".....R.....B.",
        ".........###.",
        "............."
      ]
    },
    {
      "name": "50 - La bonne personne",
      "maxMoves": 6,
      "locked": true,
      "difficulty": 50,
      "biome": "kiss",
      "solution": "LRLLLL",
      "map": [
        ".............",
        ".............",
        "....AX.......",
        "....S.....X..",
        ".............",
        "......##.....",
        "..####.......",
        ".............",
        "...###.......",
        ".....D.##....",
        ".B.....L.....",
        ".###.........",
        "............."
      ]
    }
  ]
}